LICENSE.txt
README.md
pybyrinth.py
setup.py
pybyrinth.egg-info/PKG-INFO
pybyrinth.egg-info/SOURCES.txt
pybyrinth.egg-info/dependency_links.txt
pybyrinth.egg-info/requires.txt
pybyrinth.egg-info/top_level.txt