Metadata-Version: 2.1
Name: pybyrinth
Version: 1.2.1
Summary: A Python library for creating, solving, and visualizing mazes using Depth-First Search (DFS) and Breadth-First Search (BFS) algorithms.
Home-page: https://github.com/pabblo2000/pybyrinth
Author: Pablo Álvaro Hidalgo
Author-email: palvaroh2000@gmail.com
License: MIT
Keywords: maze,labyrinth,pathfinding,search,DFS,BFS
Classifier: Programming Language :: Python :: 3
Classifier: Development Status :: 5 - Production/Stable
Classifier: Intended Audience :: Developers
Classifier: License :: OSI Approved :: MIT License
Classifier: Operating System :: OS Independent
Requires-Python: >=3.6
License-File: LICENSE.txt
Requires-Dist: numpy==1.23.5
Requires-Dist: matplotlib==3.6.2
